crud_generator/__init__.py
crud_generator/admin.py
crud_generator/apps.py
crud_generator/models.py
crud_generator/tests.py
crud_generator/views.py
crud_generator/management/__init__.py
crud_generator/management/commands/__init__.py
crud_generator/management/commands/generate_crud.py
crud_generator/migrations/__init__.py
drf_crud_generator-1.0.0.dist-info/LICENSE
drf_crud_generator-1.0.0.dist-info/METADATA
drf_crud_generator-1.0.0.dist-info/WHEEL
drf_crud_generator-1.0.0.dist-info/top_level.txt
drf_crud_generator-1.0.0.dist-info/RECORD
